Metadata-Version: 2.1
Name: stoichiometric
Version: 0.1.2
Summary: stoichiometric
